odoo/addons/excel_import_export_unidecode/README.rst
odoo/addons/excel_import_export_unidecode/__init__.py
odoo/addons/excel_import_export_unidecode/__manifest__.py
odoo/addons/excel_import_export_unidecode/i18n/es.po
odoo/addons/excel_import_export_unidecode/i18n/excel_import_export_unidecode.pot
odoo/addons/excel_import_export_unidecode/i18n/it.po
odoo/addons/excel_import_export_unidecode/models/__init__.py
odoo/addons/excel_import_export_unidecode/models/common.py
odoo/addons/excel_import_export_unidecode/models/xlsx_export.py
odoo/addons/excel_import_export_unidecode/models/xlsx_template.py
odoo/addons/excel_import_export_unidecode/readme/CONTRIBUTORS.rst
odoo/addons/excel_import_export_unidecode/readme/DESCRIPTION.rst
odoo/addons/excel_import_export_unidecode/readme/INSTALL.rst
odoo/addons/excel_import_export_unidecode/readme/ROADMAP.rst
odoo/addons/excel_import_export_unidecode/readme/USAGE.rst
odoo/addons/excel_import_export_unidecode/static/description/common_wizard.png
odoo/addons/excel_import_export_unidecode/static/description/icon.png
odoo/addons/excel_import_export_unidecode/static/description/index.html
odoo/addons/excel_import_export_unidecode/static/description/xlsx_template.png
odoo/addons/excel_import_export_unidecode/views/xlsx_template_view.xml
odoo_addon_excel_import_export_unidecode-16.0.1.0.1.13.dist-info/METADATA
odoo_addon_excel_import_export_unidecode-16.0.1.0.1.13.dist-info/WHEEL
odoo_addon_excel_import_export_unidecode-16.0.1.0.1.13.dist-info/top_level.txt
odoo_addon_excel_import_export_unidecode-16.0.1.0.1.13.dist-info/RECORD
